convenience_collection/__init__.py
convenience_collection-1.1.0.dist-info/LICENSE
convenience_collection-1.1.0.dist-info/METADATA
convenience_collection-1.1.0.dist-info/WHEEL
convenience_collection-1.1.0.dist-info/top_level.txt
convenience_collection-1.1.0.dist-info/RECORD
